gztools/__init__.py
gztools/base.py
gztools/main.py
gztools-0.0.5.dist-info/METADATA
gztools-0.0.5.dist-info/WHEEL
gztools-0.0.5.dist-info/top_level.txt
gztools-0.0.5.dist-info/RECORD
